deployee/__init__.py
deployee/deployee.py
deployee/ansible/ansible.cfg
deployee/ansible/inventory
deployee/ansible/playbook.yml
deployee/ansible/tasks/cleanup.yml
deployee/ansible/tasks/deploy.yml
deployee/ansible/tasks/django.yml
deployee/ansible/tasks/install.yml
deployee/ansible/tasks/test.yml
deployee/ansible/template/supervisor.conf.j2
deployee-0.14.0.dist-info/LICENSE
deployee-0.14.0.dist-info/METADATA
deployee-0.14.0.dist-info/WHEEL
deployee-0.14.0.dist-info/entry_points.txt
deployee-0.14.0.dist-info/top_level.txt
deployee-0.14.0.dist-info/RECORD
