Metadata-Version: 2.1
Name: deployee
Version: 0.14.0
Summary: Python tool to deploy python web application automatically
Home-page: https://github.com/WqyJh/deployee
Author: wqy
Author-email: qiyingwangwqy@gmail.com
License: UNKNOWN
Keywords: django,automation,deploy
Platform: UNKNOWN
Classifier: Programming Language :: Python :: 3 :: Only
Requires-Dist: plumbum
Requires-Dist: ansible
Requires-Dist: pyyaml
Requires-Dist: click
